freva_client/__init__.py
freva_client/__main__.py
freva_client/auth.py
freva_client/py.typed
freva_client/query.py
freva_client/cli/__init__.py
freva_client/cli/auth_cli.py
freva_client/cli/cli_app.py
freva_client/cli/cli_parser.py
freva_client/cli/cli_utils.py
freva_client/cli/databrowser_cli.py
freva_client/utils/__init__.py
freva_client/utils/auth_utils.py
freva_client/utils/databrowser_utils.py
freva_client/utils/lazy.py
freva_client/utils/lazy.pyi
freva_client/utils/logger.py
freva_client/utils/types.py
freva_client-2601.0.0.data/data/share/freva/freva.toml
freva_client-2601.0.0.dist-info/entry_points.txt
freva_client-2601.0.0.dist-info/WHEEL
freva_client-2601.0.0.dist-info/METADATA
freva_client-2601.0.0.dist-info/RECORD
