Metadata-Version: 2.4
Name: freva-client
Version: 2601.0.0
Summary: Search for climate data based on key-value pairs
Author-email: "DKRZ, Clint" <freva@dkrz.de>
Requires-Python: >=3.8
Classifier: Development Status :: 4 - Beta
Classifier: Environment :: Console
Classifier: Intended Audience :: Developers
Classifier: Intended Audience :: Science/Research
Classifier: License :: OSI Approved :: BSD License
Classifier: Operating System :: POSIX :: Linux
Classifier: Programming Language :: Python :: 3
Classifier: Programming Language :: Python :: 3.9
Classifier: Programming Language :: Python :: 3.10
Classifier: Programming Language :: Python :: 3.11
Classifier: Programming Language :: Python :: 3.12
Classifier: Programming Language :: Python :: 3.13
Classifier: Programming Language :: Python :: 3.14
Requires-Dist: appdirs
Requires-Dist: pyyaml
Requires-Dist: requests
Requires-Dist: intake_esm
Requires-Dist: rich
Requires-Dist: setuptools
Requires-Dist: tomli
Requires-Dist: typer
Requires-Dist: pandas
Requires-Dist: xarray
Requires-Dist: tox ; extra == "dev"
Project-URL: Documentation, https://freva-org.github.io/freva-nextgen
Project-URL: Issues, https://github.com/freva-org/freva-nextgen/issues
Project-URL: Source, https://github.com/freva-org/freva-nextgen/
Provides-Extra: dev
